{
    "Mandate": ["Sale", "Rent"],
    "Category": ["Apartment", "Townhouse", "Villa", "Office", "Land"],
    "Development": [],
    "Location Name": ["Runda", "Kilimani", "Kileleshwa"],
    "Size": [],
    "Unit Type": ["Acres", "Hectares", "Square Meters", "Square Feet"],
    "Bedrooms": ["Studio", 1, 2, 3, 4, 5, 6],
    "Bathrooms": [1, 2, 3, 4, 5, 6],
    "Internal Features": [
        "Air Conditioning", 
        "Backup Generator", 
        "Fibre Internet",
		"Serviced", 
        "Walk in Closet", 
        "Alarm", 
        "Ensuite",
		"Furnished", 
        "Service Charge Included",
		"Solar Hot Water System", 
        "Balcony",
        "Satellite TV"
	],
    "External Features": [
        "Borehole", 
        "Electric Fence", 
        "Gym",
		"Staff Quarters", 
        "Wheelchair Access", 
        "Sauna", 
        "CCTV",
		"Garden", 
        "Parking", 
        "Swimming Pool",
		"Power Backup for Common Areas", 
        "Intercom",
        "Club House",
        "Children's Play area"
    ]
}